linode/__init__.py
linode/api.py
linode/params.py
linode-0.4.dist-info/DESCRIPTION.rst
linode-0.4.dist-info/METADATA
linode-0.4.dist-info/metadata.json
linode-0.4.dist-info/RECORD
linode-0.4.dist-info/top_level.txt
linode-0.4.dist-info/WHEEL
