Metadata-Version: 2.0
Name: linode
Version: 0.4
Summary: Python wrapper of the Linode API
Home-page: http://github.com/ghickman/linode
Author: George Hickman
Author-email: george@ghickman.co.uk
License: MIT
Platform: UNKNOWN
Requires-Dist: requests
